apicache_cli_av/__init__.py
apicache_cli_av/api.py
apicache_cli_av/cache.py
apicache_cli_av/cli.py
apicache_cli_av/py.typed
apicache_cli_av/utils/__init__.py
apicache_cli_av/utils/json_utils.py
apicache_cli_av-0.1.7.dist-info/entry_points.txt
apicache_cli_av-0.1.7.dist-info/METADATA
apicache_cli_av-0.1.7.dist-info/WHEEL
apicache_cli_av-0.1.7.dist-info/RECORD
