Metadata-Version: 2.3
Name: apicache-cli-av
Version: 0.1.7
Summary: Tiny Typer CLI that fetches an API and caches results in SQLite (SQLModel)
License: MIT
Author: Austin Varnon
Author-email: austinvarnon@gmail.com
Requires-Python: >=3.10,<4.0
Classifier: Development Status :: 3 - Alpha
Classifier: Intended Audience :: Developers
Classifier: License :: OSI Approved :: MIT License
Classifier: Programming Language :: Python :: 3
Classifier: Programming Language :: Python :: 3.10
Classifier: Programming Language :: Python :: 3.11
Classifier: Programming Language :: Python :: 3.12
Classifier: Programming Language :: Python :: 3.13
Classifier: Topic :: Utilities
Requires-Dist: click (>=8.1.0,<8.2)
Requires-Dist: httpx (>=0.27.0,<0.28.0)
Requires-Dist: rich (>=13.7.0,<14.0.0)
Requires-Dist: sqlite-utils (>=3.36,<4.0)
Requires-Dist: sqlmodel (>=0.0.18,<0.0.19)
Requires-Dist: typer (>=0.12.0,<0.13.0)
Project-URL: Homepage, https://github.com/asvarnon/EnvAndFoundationWorkshop
Project-URL: Issues, https://github.com/asvarnon/EnvAndFoundationWorkshop/issues
Project-URL: Repository, https://github.com/asvarnon/EnvAndFoundationWorkshop
